[{"id": 1, "pitch": 0, "duration": 1.0, "dots": 1, "accidental": -1}, {"id": 2, "pitch": -1, "duration": 1.0, "dots": 1, "accidental": 1}, {"id": 3, "pitch": 3, "duration": 1.0, "dots": 1, "accidental": 0}, {"id": 4, "pitch": 2, "duration": 1.0, "dots": 1, "accidental": 0}, {"id": 5, "pitch": -2, "duration": 1.0, "dots": 0, "accidental": -1}, {"id": 6, "pitch": -3, "duration": 1.0, "dots": 0, "accidental": 0}, {"id": 7, "pitch": -3, "duration": 1.0, "dots": 1, "accidental": 1}, {"id": 8, "pitch": -4, "duration": 0.5, "dots": 0, "accidental": 0}, {"id": 9, "pitch": -3, "duration": 1.0, "dots": 0, "accidental": 0}, {"id": 10, "pitch": 0, "duration": 0.5, "dots": 0, "accidental": 0}, {"id": 11, "pitch": 1, "duration": 0.5, "dots": 0, "accidental": 0}, {"id": 12, "pitch": 2, "duration": 1.0, "dots": 1, "accidental": 0}, {"id": 13, "pitch": 0, "duration": 1.0, "dots": 0, "accidental": 0}, {"id": 14, "pitch": -2, "duration": 1.0, "dots": 0, "accidental": -3}, {"id": 15, "pitch": -3, "duration": 1.0, "dots": 0, "accidental": 0}, {"id": 16, "pitch": -1, "duration": 0.5, "dots": 0, "accidental": 0}, {"id": 17, "pitch": -2, "duration": 0.5, "dots": 0, "accidental": 0}, {"id": 18, "pitch": -3, "duration": 1.0, "dots": 1, "accidental": 0}, {"id": 19, "pitch": -4, "duration": 0.5, "dots": 0, "accidental": 0}, {"id": 20, "pitch": -3, "duration": 1.0, "dots": 0, "accidental": 0}, {"id": 21, "pitch": 0, "duration": 0.5, "dots": 0, "accidental": 0}, {"id": 22, "pitch": 1, "duration": 0.5, "dots": 0, "accidental": 0}, {"id": 23, "pitch": 2, "duration": 1.0, "dots": 1, "accidental": 0}, {"id": 24, "pitch": 1, "duration": 0.25, "dots": 0, "accidental": 0}, {"id": 25, "pitch": 0, "duration": 0.25, "dots": 0, "accidental": 0}, {"id": 26, "pitch": -2, "duration": 0.5, "dots": 0, "accidental": 0}, {"id": 27, "pitch": 2, "duration": 1.0, "dots": 1, "accidental": 0}]